{"text":"## DOTUSDT — تایم‌فریم M15\nقیمتِ لحظه‌ای: **0.805000**\nسوگیریِ بازار (H1+H4+Daily): **نزولی** — قیمت در ناحیهٔ **تخفیف (Discount)**.\nوضعیتِ این تایم‌فریم: _آزمایشی — M15 در بک‌تست اجِ پایدار نداشت_\n\n## اقدامِ الان — آمادهٔ فروش\nالان قیمت داخل/کنارِ ناحیهٔ فروش است — آمادهٔ ورود. ورود ~0.808، استاپ 0.817347، هدفِ اصلی TP2 0.789306. ریسکِ این ناحیه: کم. اول تأییدیهٔ کندلی بگیر.\n• دامیننسِ تتر: **8.68٪** (روند نامشخص) — تاریخچهٔ دامیننس هنوز کافی نیست (با هر بروزرسانی کامل‌تر می‌شود).\n\n## بهترین ستاپ — فروش (SHORT)\n• منبعِ ناحیه: اوردربلاکِ 15دقیقه‌ای | کیفیت(grade): 1/2\n• محدودهٔ ناحیه: 0.805000 تا 0.807000\n• اعتمادِ سیستم: **متوسط** — هم‌جهت با روند\n• ریسکِ این ناحیه: **متوسط** (کیفیتِ ناحیه زیرِ 2)\n• تلفیقِ سبک‌ها: **0/3** سبک هم‌جهت‌اند (—) — دقتِ آموخته‌شده با ≥0 سبکِ هم‌جهت: **46٪** (روی 15799 نمونه)\n• از استاپ‌های گذشته: ناحیه‌هایی شبیهِ این **79.5٪** استاپ خورده‌اند (روی 278 ستاپ، بازدهِ میانگین -0.385R).\n• چرا این ناحیه: هم‌جهت با سوگیریِ HTF.\n• تأییدهای کمکیِ RTM (نمایشی، نه گیتِ سیگنال): کندلِ اِنگالفِ نزولی (واکنشِ فروشندگان)، کندلِ پین‌بارِ نزولی (سایهٔ بالاییِ بلند).\n• قیمت همین حالا نزدیکِ ناحیه است (0.0 ATR) — آماده‌باش.\n\n## پلنِ معامله — مدلِ R-grid (اعتبارسنجی‌شده)\n• ورود (لبهٔ پروگزیمال): **0.805000**\n• استاپ‌لاس: **0.809490**  (ریسک ≈ 0.004490)\n• اهداف: TP1 0.800510 (1R) | TP2 **0.796020 (2R ← خروجِ اصلی)** | TP3 0.791530 (3R)\n• پیشنهادِ مدیریت: حدِ ضرر را پس از TP1 به نقطهٔ سربه‌سر ببر؛ خروجِ اصلی روی TP2 (2R).\n\n## تأییدیه‌های پیش از ورود (توصیهٔ RTM)\n1) قیمت واقعاً به ناحیه واکنش نشان دهد (کندلِ اِنگالف/پین‌بارِ نزولی داخلِ ناحیه).\n2) سشن مناسب باشد (کریپتو: نیویورک؛ طلا: لندن).\n3) فضای حداقل 2R تا ناحیهٔ مقابل باز باشد (room).\n4) خلافِ ایمپالسِ خیلی تندِ HTF وارد نشو (نشانهٔ شکستِ ناحیه).\n\n## دیدِ تکمیلی — RSI و روند\n• RSI(14) = **44.0** — خنثی.\n  (نکته: RSI و واگرایی در تایم‌فریم‌های بالاتر — 15م/1ساعته/4ساعته/روزانه — معتبرترند.)\n• آخرین واگرایی: **واگراییِ صعودی (RSI) — کفِ پایین‌تر اما RSI بالاتر** (RSI=21.1). واگرایی نشانهٔ ضعفِ روندِ فعلی است — تأییدِ کمکی، نه سیگنالِ مستقل.\n• پیش‌بینیِ جهت (هیپوتزِ سیستم، نه تضمین): **صعودی** با اطمینانِ ~53٪.\n  دلایل: سوگیریِ HTF (مخالف)؛ ستاپِ فعال (مخالف).\n  سناریو: به ناحیهٔ فروش (0.807–0.812) می‌رسد → برخورد و واکنش/برگشت (واکنش/برگشت محتمل — هم‌جهت با روندِ HTF).\n  ◦ برخورد به ناحیهٔ فروش 0.807–0.812: **احتمالِ واکنش/برگشت** (واکنش/برگشت محتمل — هم‌جهت با روندِ HTF).\n  خطِ نقطه‌چینِ روی چارت فقط مسیرِ محتمل است؛ معیارِ ورود همان پلنِ ناحیه‌ای بالاست.\n\n———\n⚠️ این یک **تحلیلِ سیستمی** است، نه سفارش. هیچ معامله‌ای به‌جای تو اجرا نمی‌شود — ورود/خروج را خودت دستی انجام می‌دهی. ریسکِ هر معامله را 1٪ نگه دار.","signal":{"symbol":"DOTUSDT","tf":"M15","price":0.805,"atr":0.00449,"bias":"نزولی","bias_val":-1,"discount":true,"premium":false,"gold":false,"tf_health":{"color":"grey","note":"آزمایشی — M15 در بک‌تست اجِ پایدار نداشت"},"zones":[{"kind":"supply","dir":"SHORT","src":"OB-1h","top":0.812,"bot":0.807,"grade":1,"entry":0.807,"sl":0.813347,"tp1":0.800653,"tp2":0.794306,"tp3":0.787959,"risk":0.006347,"dist_atr":0.45,"room_R":null,"with_trend":true,"confidence":"MEDIUM","confluence":[{"key":"engulf","fa":"کندلِ اِنگالفِ نزولی (واکنشِ فروشندگان)"},{"key":"pin","fa":"کندلِ پین‌بارِ نزولی (سایهٔ بالاییِ بلند)"}],"disc":null,"prem":false,"action":"SELL","action_fa":"فروش","actionable_now":true,"combo_score":0,"combo_styles":[],"combo_confirmed":false,"setup_type":"trend","risk_rating":{"level":"متوسط","score":2,"reasons":["کیفیتِ ناحیه زیرِ ۲"]}},{"kind":"supply","dir":"SHORT","src":"OB-15m","top":0.807,"bot":0.805,"grade":1,"entry":0.805,"sl":0.80949,"tp1":0.80051,"tp2":0.79602,"tp3":0.79153,"risk":0.00449,"dist_atr":0.0,"room_R":null,"with_trend":true,"confidence":"MEDIUM","confluence":[{"key":"engulf","fa":"کندلِ اِنگالفِ نزولی (واکنشِ فروشندگان)"},{"key":"pin","fa":"کندلِ پین‌بارِ نزولی (سایهٔ بالاییِ بلند)"}],"disc":null,"prem":false,"action":"SELL","action_fa":"فروش","actionable_now":true,"combo_score":0,"combo_styles":[],"combo_confirmed":false,"setup_type":"trend","risk_rating":{"level":"متوسط","score":2,"reasons":["کیفیتِ ناحیه زیرِ ۲"]},"combo_learned_rate":0.469,"combo_learned_n":15799,"learned_stop_rate":79.5,"learned_expR":-0.385,"learned_setups_n":278},{"kind":"supply","dir":"SHORT","src":"FL-1h","top":0.816,"bot":0.808,"grade":2,"entry":0.808,"sl":0.817347,"tp1":0.798653,"tp2":0.789306,"tp3":0.779959,"risk":0.009347,"dist_atr":0.67,"room_R":null,"with_trend":true,"confidence":"MEDIUM","confluence":[{"key":"engulf","fa":"کندلِ اِنگالفِ نزولی (واکنشِ فروشندگان)"},{"key":"pin","fa":"کندلِ پین‌بارِ نزولی (سایهٔ بالاییِ بلند)"}],"disc":null,"prem":false,"action":"SELL","action_fa":"فروش","actionable_now":true,"combo_score":0,"combo_styles":[],"combo_confirmed":false,"setup_type":"trend","risk_rating":{"level":"کم","score":1,"reasons":[]}}],"primary":{"kind":"supply","dir":"SHORT","src":"OB-15m","top":0.807,"bot":0.805,"grade":1,"entry":0.805,"sl":0.80949,"tp1":0.80051,"tp2":0.79602,"tp3":0.79153,"risk":0.00449,"dist_atr":0.0,"room_R":null,"with_trend":true,"confidence":"MEDIUM","confluence":[{"key":"engulf","fa":"کندلِ اِنگالفِ نزولی (واکنشِ فروشندگان)"},{"key":"pin","fa":"کندلِ پین‌بارِ نزولی (سایهٔ بالاییِ بلند)"}],"disc":null,"prem":false,"action":"SELL","action_fa":"فروش","actionable_now":true,"combo_score":0,"combo_styles":[],"combo_confirmed":false,"setup_type":"trend","risk_rating":{"level":"متوسط","score":2,"reasons":["کیفیتِ ناحیه زیرِ ۲"]},"combo_learned_rate":0.469,"combo_learned_n":15799,"learned_stop_rate":79.5,"learned_expR":-0.385,"learned_setups_n":278},"verdict":{"state":"SELL_NOW","action":"SELL","action_fa":"فروش","risk_level":"کم","zone":{"action":"SELL","action_fa":"فروش","dir":"SHORT","src":"FL-1h","confidence":"MEDIUM","bot":0.808,"top":0.816,"entry":0.808,"sl":0.817347,"tp2":0.789306,"tp3":0.779959,"dist_atr":0.67,"room_R":null,"combo_score":0,"combo_confirmed":false,"combo_styles":[],"setup_type":"trend","rev_target":null,"risk_level":"کم"},"text":"الان قیمت داخل/کنارِ ناحیهٔ فروش است — آمادهٔ ورود. ورود ~0.808، استاپ 0.817347، هدفِ اصلی TP2 0.789306. ریسکِ این ناحیه: کم. اول تأییدیهٔ کندلی بگیر."},"rsi":{"last":44.0,"state":"خنثی","state_fa":"","series":[{"time":1782308,"value":29.66},{"time":1782309,"value":36.03},{"time":1782310,"value":39.93},{"time":1782311,"value":41.84},{"time":1782312,"value":40.45},{"time":1782313,"value":32.37},{"time":1782314,"value":36.29},{"time":1782315,"value":27.66},{"time":1782315,"value":23.98},{"time":1782316,"value":36.18},{"time":1782317,"value":36.18},{"time":1782318,"value":32.41},{"time":1782319,"value":22.37},{"time":1782320,"value":26.07},{"time":1782321,"value":22.93},{"time":1782322,"value":22.56},{"time":1782323,"value":21.81},{"time":1782324,"value":29.39},{"time":1782324,"value":38.95},{"time":1782325,"value":38.95},{"time":1782326,"value":38.28},{"time":1782327,"value":39.4},{"time":1782328,"value":43.79},{"time":1782329,"value":42.14},{"time":1782330,"value":46.47},{"time":1782331,"value":55.44},{"time":1782332,"value":57.73},{"time":1782333,"value":57.73},{"time":1782333,"value":59.35},{"time":1782334,"value":55.9},{"time":1782335,"value":57.67},{"time":1782336,"value":60.24},{"time":1782337,"value":63.43},{"time":1782338,"value":62.09},{"time":1782339,"value":60.71},{"time":1782340,"value":59.28},{"time":1782341,"value":56.44},{"time":1782342,"value":57.53},{"time":1782342,"value":58.66},{"time":1782343,"value":59.8},{"time":1782344,"value":60.96},{"time":1782345,"value":59.12},{"time":1782346,"value":59.12},{"time":1782347,"value":57.12},{"time":1782348,"value":57.12},{"time":1782349,"value":58.74},{"time":1782350,"value":60.35},{"time":1782351,"value":60.35},{"time":1782351,"value":60.35},{"time":1782352,"value":60.35},{"time":1782353,"value":60.35},{"time":1782354,"value":51.59},{"time":1782355,"value":53.99},{"time":1782356,"value":48.78},{"time":1782357,"value":46.37},{"time":1782358,"value":41.91},{"time":1782359,"value":44.77},{"time":1782360,"value":42.52},{"time":1782360,"value":42.52},{"time":1782361,"value":48.53},{"time":1782362,"value":61.52},{"time":1782363,"value":69.75},{"time":1782364,"value":71.9},{"time":1782365,"value":64.48},{"time":1782366,"value":62.18},{"time":1782367,"value":64.88},{"time":1782368,"value":60.24},{"time":1782369,"value":61.72},{"time":1782369,"value":59.35},{"time":1782370,"value":54.82},{"time":1782371,"value":56.6},{"time":1782372,"value":56.6},{"time":1782373,"value":56.6},{"time":1782374,"value":53.94},{"time":1782375,"value":51.34},{"time":1782376,"value":51.34},{"time":1782377,"value":43.97},{"time":1782378,"value":49.21},{"time":1782378,"value":44.71},{"time":1782379,"value":47.3},{"time":1782380,"value":49.84},{"time":1782381,"value":45.16},{"time":1782382,"value":37.56},{"time":1782383,"value":35.94},{"time":1782384,"value":34.34},{"time":1782385,"value":32.76},{"time":1782386,"value":29.82},{"time":1782387,"value":28.45},{"time":1782387,"value":28.45},{"time":1782388,"value":28.45},{"time":1782389,"value":23.12},{"time":1782390,"value":40.97},{"time":1782391,"value":40.97},{"time":1782392,"value":43.51},{"time":1782393,"value":46.01},{"time":1782394,"value":25.42},{"time":1782395,"value":11.76},{"time":1782396,"value":34.78},{"time":1782396,"value":33.28},{"time":1782397,"value":32.9},{"time":1782398,"value":35.29},{"time":1782399,"value":33.99},{"time":1782400,"value":37.32},{"time":1782401,"value":37.32},{"time":1782402,"value":42.37},{"time":1782403,"value":46.98},{"time":1782404,"value":45.04},{"time":1782405,"value":38.73},{"time":1782405,"value":42.66},{"time":1782406,"value":46.37},{"time":1782407,"value":50.51},{"time":1782408,"value":49.15},{"time":1782409,"value":51.27},{"time":1782410,"value":49.06},{"time":1782411,"value":49.84},{"time":1782412,"value":44.07},{"time":1782413,"value":41.48},{"time":1782414,"value":38.45},{"time":1782414,"value":37.85},{"time":1782415,"value":36.63},{"time":1782416,"value":38.76},{"time":1782417,"value":41.92},{"time":1782418,"value":43.99},{"time":1782419,"value":41.59},{"time":1782420,"value":39.29},{"time":1782421,"value":44.78},{"time":1782422,"value":44.78},{"time":1782423,"value":48.06},{"time":1782423,"value":52.13},{"time":1782424,"value":47.15},{"time":1782425,"value":46.2},{"time":1782426,"value":44.28},{"time":1782427,"value":42.38},{"time":1782428,"value":44.92},{"time":1782429,"value":48.59},{"time":1782430,"value":45.34},{"time":1782431,"value":44.28},{"time":1782432,"value":48.2},{"time":1782432,"value":44.8},{"time":1782433,"value":42.64},{"time":1782434,"value":41.57},{"time":1782435,"value":37.48},{"time":1782436,"value":29.65},{"time":1782437,"value":28.99},{"time":1782438,"value":30.64},{"time":1782439,"value":21.51},{"time":1782440,"value":30.67},{"time":1782441,"value":29.61},{"time":1782441,"value":26.19},{"time":1782442,"value":38.26},{"time":1782443,"value":39.23},{"time":1782444,"value":43.98},{"time":1782445,"value":51.36},{"time":1782446,"value":46.92},{"time":1782447,"value":48.52},{"time":1782448,"value":47.75},{"time":1782449,"value":46.94},{"time":1782450,"value":49.68},{"time":1782450,"value":50.6},{"time":1782451,"value":50.6},{"time":1782452,"value":50.6},{"time":1782453,"value":43.65},{"time":1782454,"value":52.65},{"time":1782455,"value":56.79},{"time":1782456,"value":55.74},{"time":1782457,"value":57.43},{"time":1782458,"value":59.11},{"time":1782459,"value":57.88},{"time":1782459,"value":61.35},{"time":1782460,"value":55.23},{"time":1782461,"value":55.23},{"time":1782462,"value":52.78},{"time":1782463,"value":52.78},{"time":1782464,"value":52.78},{"time":1782465,"value":55.25},{"time":1782466,"value":55.25},{"time":1782467,"value":45.57},{"time":1782468,"value":44.37},{"time":1782468,"value":44.37},{"time":1782469,"value":44.37},{"time":1782470,"value":40.39},{"time":1782471,"value":47.19},{"time":1782472,"value":42.03},{"time":1782473,"value":42.03},{"time":1782474,"value":42.03},{"time":1782475,"value":45.73},{"time":1782476,"value":56.27},{"time":1782477,"value":43.33},{"time":1782477,"value":44.7},{"time":1782478,"value":47.43},{"time":1782479,"value":43.92},{"time":1782480,"value":55.7},{"time":1782481,"value":65.76},{"time":1782482,"value":60.1},{"time":1782483,"value":62.86},{"time":1782484,"value":56.55},{"time":1782485,"value":55.55},{"time":1782486,"value":57.96},{"time":1782486,"value":61.67},{"time":1782487,"value":66.18},{"time":1782488,"value":62.77},{"time":1782489,"value":64.1},{"time":1782490,"value":59.53},{"time":1782491,"value":62.41},{"time":1782492,"value":62.41},{"time":1782493,"value":65.94},{"time":1782494,"value":66.61},{"time":1782495,"value":63.89},{"time":1782495,"value":61.2},{"time":1782496,"value":62.88},{"time":1782497,"value":56.3},{"time":1782498,"value":58.18},{"time":1782499,"value":54.39},{"time":1782500,"value":60.01},{"time":1782501,"value":57.47},{"time":1782502,"value":58.41},{"time":1782503,"value":52.16},{"time":1782504,"value":57.11},{"time":1782504,"value":58.04},{"time":1782505,"value":50.88},{"time":1782506,"value":50.88},{"time":1782507,"value":48.56},{"time":1782508,"value":49.79},{"time":1782509,"value":53.4},{"time":1782510,"value":46.25},{"time":1782511,"value":46.25},{"time":1782512,"value":43.97},{"time":1782513,"value":49.34},{"time":1782513,"value":50.61},{"time":1782514,"value":50.61},{"time":1782515,"value":47.82},{"time":1782516,"value":47.82},{"time":1782517,"value":47.82},{"time":1782518,"value":49.56},{"time":1782519,"value":43.35},{"time":1782520,"value":40.61},{"time":1782521,"value":44.39},{"time":1782522,"value":42.92},{"time":1782522,"value":44.89},{"time":1782523,"value":44.89},{"time":1782524,"value":43.16},{"time":1782525,"value":49.45},{"time":1782526,"value":57.82},{"time":1782527,"value":61.9},{"time":1782528,"value":59.82},{"time":1782529,"value":53.97},{"time":1782530,"value":58.36},{"time":1782531,"value":56.43},{"time":1782531,"value":47.9},{"time":1782532,"value":51.08},{"time":1782533,"value":51.08},{"time":1782534,"value":47.7},{"time":1782535,"value":43.1},{"time":1782536,"value":43.1},{"time":1782537,"value":40.1},{"time":1782538,"value":44.27},{"time":1782539,"value":49.91},{"time":1782540,"value":40.98},{"time":1782540,"value":40.98},{"time":1782541,"value":44.8},{"time":1782542,"value":41.88},{"time":1782543,"value":40.46},{"time":1782544,"value":42.56},{"time":1782545,"value":41.0},{"time":1782546,"value":43.24},{"time":1782547,"value":39.98},{"time":1782548,"value":39.98},{"time":1782549,"value":36.77},{"time":1782549,"value":41.8},{"time":1782550,"value":40.08},{"time":1782551,"value":42.62},{"time":1782552,"value":45.13},{"time":1782553,"value":47.6},{"time":1782554,"value":47.6},{"time":1782555,"value":41.16},{"time":1782556,"value":46.37},{"time":1782557,"value":42.33},{"time":1782558,"value":40.44},{"time":1782558,"value":35.33},{"time":1782559,"value":35.33},{"time":1782560,"value":45.9},{"time":1782561,"value":40.55},{"time":1782562,"value":45.14},{"time":1782563,"value":45.14},{"time":1782564,"value":47.49},{"time":1782565,"value":49.81},{"time":1782566,"value":49.81},{"time":1782567,"value":54.47},{"time":1782567,"value":54.47},{"time":1782568,"value":58.89},{"time":1782569,"value":55.97},{"time":1782570,"value":50.55},{"time":1782571,"value":48.05},{"time":1782572,"value":60.64},{"time":1782573,"value":55.79},{"time":1782574,"value":55.79},{"time":1782575,"value":55.79},{"time":1782576,"value":50.72},{"time":1782576,"value":48.35},{"time":1782577,"value":50.82},{"time":1782578,"value":46.07},{"time":1782579,"value":35.39},{"time":1782580,"value":33.98},{"time":1782581,"value":32.57},{"time":1782582,"value":29.92},{"time":1782583,"value":29.92},{"time":1782584,"value":28.56},{"time":1782585,"value":28.56},{"time":1782585,"value":32.12},{"time":1782586,"value":32.12},{"time":1782587,"value":24.92},{"time":1782588,"value":24.92},{"time":1782589,"value":24.92},{"time":1782590,"value":28.9},{"time":1782591,"value":32.74},{"time":1782592,"value":29.33},{"time":1782593,"value":33.08},{"time":1782594,"value":31.29},{"time":1782594,"value":29.57},{"time":1782595,"value":21.81},{"time":1782596,"value":20.83},{"time":1782597,"value":18.19},{"time":1782598,"value":15.38},{"time":1782599,"value":15.38},{"time":1782600,"value":25.39},{"time":1782601,"value":23.4},{"time":1782602,"value":29.35},{"time":1782603,"value":29.35},{"time":1782603,"value":28.09},{"time":1782604,"value":34.2},{"time":1782605,"value":31.33},{"time":1782606,"value":26.54},{"time":1782607,"value":24.52},{"time":1782608,"value":21.07},{"time":1782609,"value":31.46},{"time":1782610,"value":31.46},{"time":1782611,"value":31.46},{"time":1782612,"value":38.99},{"time":1782612,"value":36.14},{"time":1782613,"value":36.14},{"time":1782614,"value":45.39},{"time":1782615,"value":52.76},{"time":1782616,"value":50.91},{"time":1782617,"value":47.34},{"time":1782618,"value":52.7},{"time":1782619,"value":50.84},{"time":1782620,"value":52.64},{"time":1782621,"value":56.11},{"time":1782621,"value":52.01},{"time":1782622,"value":43.47},{"time":1782623,"value":39.3},{"time":1782624,"value":44.98},{"time":1782625,"value":42.15},{"time":1782626,"value":36.04},{"time":1782627,"value":39.8},{"time":1782628,"value":43.38},{"time":1782629,"value":45.14},{"time":1782630,"value":51.62},{"time":1782630,"value":45.8},{"time":1782631,"value":51.67},{"time":1782632,"value":53.04},{"time":1782633,"value":49.99},{"time":1782634,"value":51.49},{"time":1782635,"value":57.04},{"time":1782636,"value":53.73},{"time":1782637,"value":53.73},{"time":1782638,"value":50.34},{"time":1782639,"value":47.13},{"time":1782639,"value":36.99},{"time":1782640,"value":42.03},{"time":1782641,"value":38.7},{"time":1782642,"value":42.0},{"time":1782643,"value":40.81},{"time":1782644,"value":39.61},{"time":1782645,"value":43.21},{"time":1782646,"value":44.98},{"time":1782647,"value":48.44},{"time":1782648,"value":48.44},{"time":1782648,"value":51.94},{"time":1782649,"value":46.81},{"time":1782650,"value":48.63},{"time":1782651,"value":42.37},{"time":1782652,"value":40.95},{"time":1782653,"value":40.95},{"time":1782654,"value":34.3},{"time":1782655,"value":44.09},{"time":1782656,"value":50.45},{"time":1782657,"value":46.2},{"time":1782657,"value":49.27},{"time":1782658,"value":45.11},{"time":1782659,"value":45.11},{"time":1782660,"value":46.85},{"time":1782661,"value":53.21},{"time":1782662,"value":49.99},{"time":1782663,"value":51.56},{"time":1782664,"value":46.79},{"time":1782665,"value":50.11},{"time":1782666,"value":46.96},{"time":1782666,"value":43.98},{"time":1782667,"value":43.98}]},"divergences":[{"time":1782361,"type":"bull","price":0.879,"rsi":48.5,"fa":"واگراییِ صعودی (RSI) — کفِ پایین‌تر اما RSI بالاتر"},{"time":1782497,"type":"bear","price":0.868,"rsi":56.3,"fa":"واگراییِ نزولی (RSI) — سقفِ بالاتر اما RSI پایین‌تر"},{"time":1782608,"type":"bull","price":0.804,"rsi":21.1,"fa":"واگراییِ صعودی (RSI) — کفِ پایین‌تر اما RSI بالاتر"}],"projection":{"dir":"صعودی","dir_val":1,"confidence":0.53,"notes":["سوگیریِ HTF (مخالف)","ستاپِ فعال (مخالف)"],"rsi_state":"خنثی","points":[{"time":1782668700,"value":0.806696},{"time":1782669600,"value":0.807},{"time":1782670500,"value":0.808021},{"time":1782671400,"value":0.808093},{"time":1782672300,"value":0.807839},{"time":1782673200,"value":0.807247},{"time":1782674100,"value":0.806395},{"time":1782675000,"value":0.805432},{"time":1782675900,"value":0.804531},{"time":1782676800,"value":0.803838},{"time":1782677700,"value":0.803437},{"time":1782678600,"value":0.803327},{"time":1782679500,"value":0.803425},{"time":1782680400,"value":0.8036},{"time":1782681300,"value":0.80371},{"time":1782682200,"value":0.803644},{"time":1782683100,"value":0.803357},{"time":1782684000,"value":0.802877},{"time":1782684900,"value":0.802298},{"time":1782685800,"value":0.801745},{"time":1782686700,"value":0.80134},{"time":1782687600,"value":0.801164},{"time":1782688500,"value":0.801234},{"time":1782689400,"value":0.801496},{"time":1782690300,"value":0.801845},{"time":1782691200,"value":0.802157},{"time":1782692100,"value":0.802319},{"time":1782693000,"value":0.802265},{"time":1782693900,"value":0.801989},{"time":1782694800,"value":0.80155},{"time":1782695700,"value":0.801043},{"time":1782696600,"value":0.800579},{"time":1782697500,"value":0.800248},{"time":1782698400,"value":0.800095},{"time":1782699300,"value":0.800109},{"time":1782700200,"value":0.80023},{"time":1782701100,"value":0.80037},{"time":1782702000,"value":0.800438},{"time":1782702900,"value":0.800369},{"time":1782703800,"value":0.800146},{"time":1782704700,"value":0.799799},{"time":1782705600,"value":0.799398},{"time":1782706500,"value":0.799034},{"time":1782707400,"value":0.798787},{"time":1782708300,"value":0.79871},{"time":1782709200,"value":0.798809},{"time":1782710100,"value":0.799044},{"time":1782711000,"value":0.799345}],"events":[{"type":"bounce","time":1782669600,"price":0.807,"zone":{"src":"OB-1h","dir":"SHORT","bot":0.807,"top":0.812,"action_fa":"فروش"},"score":3,"reason":"واکنش/برگشت محتمل — هم‌جهت با روندِ HTF"}],"scenario":"سناریو: به ناحیهٔ فروش (0.807–0.812) می‌رسد → برخورد و واکنش/برگشت (واکنش/برگشت محتمل — هم‌جهت با روندِ HTF).","learned_rate":null,"learned_n":0},"dominance":{"usdt_d":8.68,"trend":"نامشخص","slope":null,"crypto_bias":0,"note":"تاریخچهٔ دامیننس هنوز کافی نیست (با هر بروزرسانی کامل‌تر می‌شود).","samples":2},"setup_lessons":{"overall":{"n":321,"stops":244,"win_rate":24.0,"stop_rate":76.0,"expR":-0.277},"by":{"setup_type":{"reversal":{"n":121,"stops":112,"win_rate":7.4,"stop_rate":92.6,"expR":-0.768},"trend":{"n":99,"stops":70,"win_rate":29.3,"stop_rate":70.7,"expR":-0.121}},"combo_confirmed":{"False":{"n":278,"stops":221,"win_rate":20.5,"stop_rate":79.5,"expR":-0.385},"True":{"n":42,"stops":23,"win_rate":45.2,"stop_rate":54.8,"expR":0.357}},"confidence":{"LOW":{"n":138,"stops":127,"win_rate":8.0,"stop_rate":92.0,"expR":-0.761},"MEDIUM":{"n":84,"stops":56,"win_rate":33.3,"stop_rate":66.7,"expR":0.0}},"src":{"OB-1h":{"n":126,"stops":85,"win_rate":32.5,"stop_rate":67.5,"expR":-0.024},"OB-15m":{"n":71,"stops":56,"win_rate":21.1,"stop_rate":78.9,"expR":-0.366},"FL-1h":{"n":123,"stops":103,"win_rate":16.3,"stop_rate":83.7,"expR":-0.512}},"dir":{"LONG":{"n":182,"stops":151,"win_rate":17.0,"stop_rate":83.0,"expR":-0.489},"SHORT":{"n":139,"stops":93,"win_rate":33.1,"stop_rate":66.9,"expR":0.0}},"with_trend":{"True":{"n":190,"stops":122,"win_rate":35.8,"stop_rate":64.2,"expR":0.074},"False":{"n":131,"stops":122,"win_rate":6.9,"stop_rate":93.1,"expR":-0.786}}}}}}